shakah/__init__.py
shakah/_core/__init__.py
shakah/_core/definitions.py
shakah/_core/sourcing.py
shakah/config.py
shakah/conn.py
shakah/dysettings.py
shakah/enums.py
shakah/errors.py
shakah/gears/__init__.py
shakah/gears/structs/__init__.py
shakah/gears/structs/vehicles.py
shakah/main.py
shakah/models/user.py
shakah/typings.py
shakah/utils/__init__.py
shakah/utils/criterias.py
shakah/utils/decorators/__init__.py
shakah/utils/decorators/classes.py
shakah/utils/decorators/runners.py
shakah/utils/decorators/sqlclass.py
shakah/utils/knoting.py
shakah/utils/transforms.py
shakah-2.0.1.dist-info/WHEEL
shakah-2.0.1.dist-info/METADATA
shakah-2.0.1.dist-info/RECORD
