Metadata-Version: 2.1
Name: shakah
Version: 2.0.1
Summary: 
Author: kivo360
Author-email: kivo360@gmail.com
Requires-Python: >=3.9,<4.0
Classifier: Programming Language :: Python :: 3
Classifier: Programming Language :: Python :: 3.10
Classifier: Programming Language :: Python :: 3.9
Requires-Dist: cytoolz (>=0.11.2,<0.12.0)
Requires-Dist: decorator (>=5.1.1,<6.0.0)
Requires-Dist: devtools (>=0.8.0,<0.9.0)
Requires-Dist: dynaconf[redis,vault] (>=3.1.7,<4.0.0)
Requires-Dist: fastcore (>=1.3.27,<2.0.0)
Requires-Dist: import-linter (>=1.2.6,<2.0.0)
Requires-Dist: loguru (>=0.5.3,<0.6.0)
Requires-Dist: psycopg2 (>=2.9.3,<3.0.0)
Requires-Dist: pydantic[email,dotenv] (>=1.9.0,<2.0.0)
Requires-Dist: sqlmodel (>=0.0.6,<0.0.7)
